arknights_mower/__init__.py
arknights_mower/__main__.py
arknights_mower/command.py
arknights_mower/strategy.py
arknights_mower/data/__init__.py
arknights_mower/data/agent.json
arknights_mower/data/arrange_order.json
arknights_mower/data/base.json
arknights_mower/data/chapter.json
arknights_mower/data/clue.json
arknights_mower/data/key_mapping.json
arknights_mower/data/level.json
arknights_mower/data/ocr.json
arknights_mower/data/recruit.json
arknights_mower/data/recruit_result.json
arknights_mower/data/scene.json
arknights_mower/data/shop.json
arknights_mower/data/weekly.json
arknights_mower/data/zone.json
arknights_mower/fonts/README.md
arknights_mower/fonts/SourceHanSansCN-Medium.otf
arknights_mower/models/README.md
arknights_mower/models/crnn_lite_lstm.onnx
arknights_mower/models/dbnet.onnx
arknights_mower/models/svm.model
arknights_mower/ocr/__init__.py
arknights_mower/ocr/config.py
arknights_mower/ocr/crnn.py
arknights_mower/ocr/dbnet.py
arknights_mower/ocr/decode.py
arknights_mower/ocr/keys.py
arknights_mower/ocr/model.py
arknights_mower/ocr/ocrspace.py
arknights_mower/ocr/rectify.py
arknights_mower/ocr/utils.py
arknights_mower/resources/12cadpa.png
arknights_mower/resources/README.md
arknights_mower/resources/agent_in_dormitory.png
arknights_mower/resources/agent_on_shift.png
arknights_mower/resources/agent_resting.png
arknights_mower/resources/agent_token.png
arknights_mower/resources/agent_token_1080_1440.png
arknights_mower/resources/agent_token_900_1440.png
arknights_mower/resources/agent_unlock.png
arknights_mower/resources/all_in.png
arknights_mower/resources/arrange_blue_yes.png
arknights_mower/resources/arrange_check_in.png
arknights_mower/resources/arrange_check_in_on.png
arknights_mower/resources/arrange_clean.png
arknights_mower/resources/arrange_confirm.png
arknights_mower/resources/arrange_empty_room.png
arknights_mower/resources/arrange_feeling.png
arknights_mower/resources/arrange_non_check_in.png
arknights_mower-3.4.4.dist-info/LICENSE
arknights_mower-3.4.4.dist-info/METADATA
arknights_mower-3.4.4.dist-info/WHEEL
arknights_mower-3.4.4.dist-info/entry_points.txt
arknights_mower-3.4.4.dist-info/top_level.txt
arknights_mower-3.4.4.dist-info/RECORD
