Metadata-Version: 2.1
Name: arknights-mower
Version: 3.4.4
Summary: Arknights Helper based on ADB and Python
Home-page: https://github.com/Konano/arknights-mower
Author: Konano
Author-email: w@nano.ac
Classifier: Development Status :: 5 - Production/Stable
Classifier: Programming Language :: Python :: 3.5
Classifier: Programming Language :: Python :: 3.6
Classifier: Programming Language :: Python :: 3.7
Classifier: Programming Language :: Python :: 3.8
Classifier: Programming Language :: Python :: 3.9
Classifier: Programming Language :: Python :: 3.10
Classifier: Programming Language :: Python :: 3.11
Classifier: Topic :: Games/Entertainment
Classifier: License :: OSI Approved :: MIT License
Classifier: Operating System :: OS Independent
License-File: LICENSE
Requires-Dist: colorlog
Requires-Dist: opencv-python
Requires-Dist: matplotlib
Requires-Dist: numpy
Requires-Dist: scikit-image ==0.18.3
Requires-Dist: scikit-learn >=1
Requires-Dist: onnxruntime
Requires-Dist: pyclipper
Requires-Dist: shapely
Requires-Dist: tornado
Requires-Dist: requests
Requires-Dist: ruamel.yaml
Requires-Dist: schedule
